net_login.py
campnet_login-0.1.3.dist-info/licenses/LICENSE
campnet_login-0.1.3.dist-info/METADATA
campnet_login-0.1.3.dist-info/WHEEL
campnet_login-0.1.3.dist-info/entry_points.txt
campnet_login-0.1.3.dist-info/top_level.txt
campnet_login-0.1.3.dist-info/RECORD
