Metadata-Version: 2.4
Name: campnet-login
Version: 0.1.3
Summary: Login to Campnet via GUI automation.
Author: Vineet Krishna
License: MIT License
License-File: LICENSE
Requires-Dist: pyautogui>=0.9.54
Dynamic: license-file
